emma/__init__.py
emma/__main__.py
emma/admin.py
emma/asgi.py
emma/middleware.py
emma/models.py
emma/settings.py
emma/storage.py
emma/urls.py
emma/views.py
emma/wsgi.py
emma-0.0.1.dist-info/METADATA
emma-0.0.1.dist-info/WHEEL
emma-0.0.1.dist-info/entry_points.txt
emma-0.0.1.dist-info/top_level.txt
emma-0.0.1.dist-info/RECORD
