Metadata-Version: 2.1
Name: emma
Version: 0.0.1
Summary: Emma -- Productivity analysis tool.
Home-page: https://grantjenks.com/docs/emma/
Author: Grant Jenks
Author-email: contact@grantjenks.com
License: Apache 2.0
Project-URL: Documentation, https://grantjenks.com/docs/emma/
Project-URL: Source, https://github.com/grantjenks/emma
Project-URL: Tracker, https://github.com/grantjenks/emma/issues
Platform: UNKNOWN
Classifier: Development Status :: 3 - Alpha
Classifier: Intended Audience :: End Users/Desktop
Classifier: License :: OSI Approved :: Apache Software License
Classifier: Natural Language :: English
Classifier: Programming Language :: Python
Classifier: Programming Language :: Python :: 3
Classifier: Programming Language :: Python :: 3.7
Classifier: Programming Language :: Python :: 3.8
Classifier: Programming Language :: Python :: 3.9
Classifier: Programming Language :: Python :: 3.10
Classifier: Programming Language :: Python :: Implementation :: CPython
Requires-Python: >=3
Requires-Dist: appdirs
Requires-Dist: django (==3.2.*)
Requires-Dist: gunicorn
Requires-Dist: pandas
Requires-Dist: pillow
Requires-Dist: plotly
Requires-Dist: rumps
